{"dependencies":[{"name":"/Users/owner/Documents/finddit/package.json","includedInParent":true,"mtime":1519735195000},{"name":"./redditAPI","loc":{"line":1,"column":19}}],"generated":{"js":"'use strict';\n\nvar _redditAPI = require('./redditAPI');\n\nvar _redditAPI2 = _interopRequireDefault(_redditAPI);\n\nfunction _interopRequireDefault(obj) { return obj && obj.__esModule ? obj : { default: obj }; }\n\nvar searchForm = document.getElementById('search-form');\nvar searchInput = document.getElementById('search-input');\n\n//Form Event Listener\nsearchForm.addEventListener('submit', function (e) {\n    e.preventDefault();\n\n    //Get search term\n    var searchTerm = searchInput.value;\n\n    //Get sort\n    var sortBy = document.querySelector('input[name=\"sortby\"]:checked').value;\n\n    // Get Limit\n    var searchLimit = document.getElementById('limit').value;\n\n    //Check Input\n\n    if (searchTerm === '') {\n        //Show message\n        showMessage('Please add a search term!', 'alert-danger');\n    }\n\n    //Clear input\n    searchInput.value = '';\n\n    //Search Reddit\n    _redditAPI2.default.search(searchTerm, searchLimit, sortBy).then(function (results) {\n        var output = '<div class=\"card-columns\">';\n        //Loop through posts\n\n        results.forEach(function (post) {\n            //Check for image;\n            var image = post.preview ? post.preview.images[0].source.url : 'https://marketingland.com/wp-content/ml-loads/2014/07/reddit-combo-1920-800x450.png';\n            output += '\\n                <div class=\"card\" >\\n                    <img class=\"card-img-top\" src=' + image + ' alt=\"Card image cap\">\\n                    <div class=\"card-body\">\\n                    <h5 class=\"card-title\">' + truncateText(post.title, 50) + '...</h5>\\n                    <p class=\"card-text\">' + truncateText(post.selftext, 100) + '</p>\\n                    <a href=' + post.url + ' target=\"_blank\" class=\"btn btn-primary\">Read More</a>\\n                    <hr>\\n                    <span class=\"badge badge-secondary\"> Subreddit: ' + post.subreddit + ' </span>\\n                    <span class=\"badge badge-dark\"> Score: ' + post.score + ' </span>\\n                    </div>\\n                </div>\\n                ';\n        });\n        output += '</div>';\n        document.getElementById('results').innerHTML = output;\n    });\n});\n\n//Show Message\n\nfunction showMessage(message, className) {\n    //create div\n    var div = document.createElement('div');\n    //Add classes\n    div.className = 'alert ' + className;\n    //Add text\n    div.appendChild(document.createTextNode(message));\n    //Get Parent \n    var searchContainer = document.getElementById('search-container');\n    //Get Search\n    var search = document.getElementById('search');\n\n    //Insert Message\n    searchContainer.insertBefore(div, search);\n\n    //Timeout alert\n    setTimeout(function () {\n        return document.querySelector('.alert').remove();\n    }, 3000);\n}\n//Truncate Text\n\nfunction truncateText(text, limit) {\n    var shortend = text.indexOf(' ', limit);\n\n    if (shortend == -1) return text;\n    return text.substring(0, shortend);\n}","map":{"mappings":[{"generated":{"line":3,"column":0},"source":"index.js","original":{"line":1,"column":0}},{"generated":{"line":9,"column":0},"source":"index.js","original":{"line":3,"column":0}},{"name":"searchForm","generated":{"line":9,"column":4},"source":"index.js","original":{"line":3,"column":6}},{"name":"document","generated":{"line":9,"column":17},"source":"index.js","original":{"line":3,"column":19}},{"name":"getElementById","generated":{"line":9,"column":26},"source":"index.js","original":{"line":3,"column":28}},{"generated":{"line":9,"column":40},"source":"index.js","original":{"line":3,"column":19}},{"generated":{"line":9,"column":41},"source":"index.js","original":{"line":3,"column":43}},{"generated":{"line":9,"column":54},"source":"index.js","original":{"line":3,"column":19}},{"generated":{"line":9,"column":55},"source":"index.js","original":{"line":3,"column":0}},{"generated":{"line":10,"column":0},"source":"index.js","original":{"line":4,"column":0}},{"name":"searchInput","generated":{"line":10,"column":4},"source":"index.js","original":{"line":4,"column":6}},{"name":"document","generated":{"line":10,"column":18},"source":"index.js","original":{"line":4,"column":20}},{"name":"getElementById","generated":{"line":10,"column":27},"source":"index.js","original":{"line":4,"column":29}},{"generated":{"line":10,"column":41},"source":"index.js","original":{"line":4,"column":20}},{"generated":{"line":10,"column":42},"source":"index.js","original":{"line":4,"column":44}},{"generated":{"line":10,"column":56},"source":"index.js","original":{"line":4,"column":20}},{"generated":{"line":10,"column":57},"source":"index.js","original":{"line":4,"column":0}},{"generated":{"line":12,"column":0},"source":"index.js","original":{"line":7,"column":0}},{"name":"searchForm","generated":{"line":13,"column":0},"source":"index.js","original":{"line":8,"column":0}},{"name":"addEventListener","generated":{"line":13,"column":11},"source":"index.js","original":{"line":8,"column":11}},{"generated":{"line":13,"column":27},"source":"index.js","original":{"line":8,"column":0}},{"generated":{"line":13,"column":28},"source":"index.js","original":{"line":8,"column":28}},{"generated":{"line":13,"column":36},"source":"index.js","original":{"line":8,"column":0}},{"generated":{"line":13,"column":38},"source":"index.js","original":{"line":8,"column":38}},{"generated":{"line":13,"column":51},"source":"index.js","original":{"line":8,"column":43}},{"name":"e","generated":{"line":14,"column":0},"source":"index.js","original":{"line":9,"column":4}},{"name":"preventDefault","generated":{"line":14,"column":6},"source":"index.js","original":{"line":9,"column":6}},{"generated":{"line":14,"column":20},"source":"index.js","original":{"line":9,"column":4}},{"generated":{"line":16,"column":0},"source":"index.js","original":{"line":11,"column":4}},{"generated":{"line":17,"column":0},"source":"index.js","original":{"line":12,"column":4}},{"name":"searchTerm","generated":{"line":17,"column":8},"source":"index.js","original":{"line":12,"column":10}},{"name":"searchInput","generated":{"line":17,"column":21},"source":"index.js","original":{"line":12,"column":23}},{"name":"value","generated":{"line":17,"column":33},"source":"index.js","original":{"line":12,"column":35}},{"generated":{"line":17,"column":38},"source":"index.js","original":{"line":12,"column":4}},{"generated":{"line":19,"column":0},"source":"index.js","original":{"line":14,"column":4}},{"generated":{"line":20,"column":0},"source":"index.js","original":{"line":15,"column":4}},{"name":"sortBy","generated":{"line":20,"column":8},"source":"index.js","original":{"line":15,"column":10}},{"name":"document","generated":{"line":20,"column":17},"source":"index.js","original":{"line":15,"column":19}},{"name":"querySelector","generated":{"line":20,"column":26},"source":"index.js","original":{"line":15,"column":28}},{"generated":{"line":20,"column":39},"source":"index.js","original":{"line":15,"column":19}},{"generated":{"line":20,"column":40},"source":"index.js","original":{"line":15,"column":42}},{"generated":{"line":20,"column":70},"source":"index.js","original":{"line":15,"column":19}},{"name":"value","generated":{"line":20,"column":72},"source":"index.js","original":{"line":15,"column":74}},{"generated":{"line":20,"column":77},"source":"index.js","original":{"line":15,"column":4}},{"generated":{"line":22,"column":0},"source":"index.js","original":{"line":17,"column":4}},{"generated":{"line":23,"column":0},"source":"index.js","original":{"line":18,"column":4}},{"name":"searchLimit","generated":{"line":23,"column":8},"source":"index.js","original":{"line":18,"column":10}},{"name":"document","generated":{"line":23,"column":22},"source":"index.js","original":{"line":18,"column":24}},{"name":"getElementById","generated":{"line":23,"column":31},"source":"index.js","original":{"line":18,"column":33}},{"generated":{"line":23,"column":45},"source":"index.js","original":{"line":18,"column":24}},{"generated":{"line":23,"column":46},"source":"index.js","original":{"line":18,"column":48}},{"generated":{"line":23,"column":53},"source":"index.js","original":{"line":18,"column":24}},{"name":"value","generated":{"line":23,"column":55},"source":"index.js","original":{"line":18,"column":57}},{"generated":{"line":23,"column":60},"source":"index.js","original":{"line":18,"column":4}},{"generated":{"line":25,"column":0},"source":"index.js","original":{"line":20,"column":4}},{"generated":{"line":27,"column":0},"source":"index.js","original":{"line":22,"column":4}},{"name":"searchTerm","generated":{"line":27,"column":8},"source":"index.js","original":{"line":22,"column":7}},{"generated":{"line":27,"column":23},"source":"index.js","original":{"line":22,"column":22}},{"generated":{"line":27,"column":25},"source":"index.js","original":{"line":22,"column":4}},{"generated":{"line":27,"column":27},"source":"index.js","original":{"line":22,"column":26}},{"generated":{"line":28,"column":0},"source":"index.js","original":{"line":23,"column":8}},{"name":"showMessage","generated":{"line":29,"column":0},"source":"index.js","original":{"line":24,"column":8}},{"generated":{"line":29,"column":20},"source":"index.js","original":{"line":24,"column":20}},{"generated":{"line":29,"column":47},"source":"index.js","original":{"line":24,"column":8}},{"generated":{"line":29,"column":49},"source":"index.js","original":{"line":24,"column":49}},{"generated":{"line":29,"column":63},"source":"index.js","original":{"line":24,"column":8}},{"generated":{"line":30,"column":0},"source":"index.js","original":{"line":25,"column":5}},{"generated":{"line":32,"column":0},"source":"index.js","original":{"line":27,"column":4}},{"name":"searchInput","generated":{"line":33,"column":0},"source":"index.js","original":{"line":28,"column":4}},{"name":"value","generated":{"line":33,"column":16},"source":"index.js","original":{"line":28,"column":16}},{"generated":{"line":33,"column":21},"source":"index.js","original":{"line":28,"column":4}},{"generated":{"line":33,"column":24},"source":"index.js","original":{"line":28,"column":24}},{"generated":{"line":33,"column":26},"source":"index.js","original":{"line":28,"column":4}},{"generated":{"line":35,"column":0},"source":"index.js","original":{"line":30,"column":4}},{"generated":{"line":36,"column":0},"source":"index.js","original":{"line":31,"column":4}},{"name":"search","generated":{"line":36,"column":24},"source":"index.js","original":{"line":31,"column":11}},{"generated":{"line":36,"column":30},"source":"index.js","original":{"line":31,"column":4}},{"name":"searchTerm","generated":{"line":36,"column":31},"source":"index.js","original":{"line":31,"column":18}},{"generated":{"line":36,"column":41},"source":"index.js","original":{"line":31,"column":4}},{"name":"searchLimit","generated":{"line":36,"column":43},"source":"index.js","original":{"line":31,"column":30}},{"generated":{"line":36,"column":54},"source":"index.js","original":{"line":31,"column":4}},{"name":"sortBy","generated":{"line":36,"column":56},"source":"index.js","original":{"line":31,"column":43}},{"generated":{"line":36,"column":62},"source":"index.js","original":{"line":31,"column":4}},{"name":"then","generated":{"line":36,"column":64},"source":"index.js","original":{"line":32,"column":9}},{"generated":{"line":36,"column":68},"source":"index.js","original":{"line":31,"column":4}},{"generated":{"line":36,"column":69},"source":"index.js","original":{"line":32,"column":14}},{"generated":{"line":36,"column":88},"source":"index.js","original":{"line":32,"column":25}},{"generated":{"line":37,"column":0},"source":"index.js","original":{"line":33,"column":12}},{"name":"output","generated":{"line":37,"column":12},"source":"index.js","original":{"line":33,"column":16}},{"generated":{"line":37,"column":21},"source":"index.js","original":{"line":33,"column":25}},{"generated":{"line":37,"column":49},"source":"index.js","original":{"line":33,"column":12}},{"generated":{"line":38,"column":0},"source":"index.js","original":{"line":34,"column":12}},{"name":"results","generated":{"line":40,"column":0},"source":"index.js","original":{"line":36,"column":12}},{"name":"forEach","generated":{"line":40,"column":16},"source":"index.js","original":{"line":36,"column":20}},{"generated":{"line":40,"column":23},"source":"index.js","original":{"line":36,"column":12}},{"generated":{"line":40,"column":24},"source":"index.js","original":{"line":36,"column":28}},{"generated":{"line":40,"column":40},"source":"index.js","original":{"line":36,"column":36}},{"generated":{"line":41,"column":0},"source":"index.js","original":{"line":37,"column":16}},{"generated":{"line":42,"column":0},"source":"index.js","original":{"line":38,"column":16}},{"name":"image","generated":{"line":42,"column":16},"source":"index.js","original":{"line":38,"column":22}},{"name":"post","generated":{"line":42,"column":24},"source":"index.js","original":{"line":38,"column":30}},{"name":"preview","generated":{"line":42,"column":29},"source":"index.js","original":{"line":38,"column":35}},{"generated":{"line":42,"column":36},"source":"index.js","original":{"line":38,"column":30}},{"name":"post","generated":{"line":42,"column":39},"source":"index.js","original":{"line":38,"column":45}},{"name":"preview","generated":{"line":42,"column":44},"source":"index.js","original":{"line":38,"column":50}},{"generated":{"line":42,"column":51},"source":"index.js","original":{"line":38,"column":45}},{"name":"images","generated":{"line":42,"column":52},"source":"index.js","original":{"line":38,"column":58}},{"generated":{"line":42,"column":58},"source":"index.js","original":{"line":38,"column":45}},{"generated":{"line":42,"column":59},"source":"index.js","original":{"line":38,"column":65}},{"generated":{"line":42,"column":60},"source":"index.js","original":{"line":38,"column":45}},{"name":"source","generated":{"line":42,"column":62},"source":"index.js","original":{"line":38,"column":68}},{"generated":{"line":42,"column":68},"source":"index.js","original":{"line":38,"column":45}},{"name":"url","generated":{"line":42,"column":69},"source":"index.js","original":{"line":38,"column":75}},{"generated":{"line":42,"column":72},"source":"index.js","original":{"line":38,"column":30}},{"generated":{"line":42,"column":75},"source":"index.js","original":{"line":38,"column":81}},{"generated":{"line":42,"column":160},"source":"index.js","original":{"line":38,"column":16}},{"name":"output","generated":{"line":43,"column":0},"source":"index.js","original":{"line":39,"column":16}},{"name":"image","generated":{"line":43,"column":116},"source":"index.js","original":{"line":41,"column":52}},{"generated":{"line":43,"column":121},"source":"index.js","original":{"line":39,"column":16}},{"name":"truncateText","generated":{"line":43,"column":241},"source":"index.js","original":{"line":43,"column":45}},{"name":"post","generated":{"line":43,"column":254},"source":"index.js","original":{"line":43,"column":58}},{"name":"title","generated":{"line":43,"column":259},"source":"index.js","original":{"line":43,"column":63}},{"generated":{"line":43,"column":264},"source":"index.js","original":{"line":43,"column":45}},{"generated":{"line":43,"column":266},"source":"index.js","original":{"line":43,"column":70}},{"generated":{"line":43,"column":268},"source":"index.js","original":{"line":43,"column":45}},{"generated":{"line":43,"column":269},"source":"index.js","original":{"line":39,"column":16}},{"name":"truncateText","generated":{"line":43,"column":328},"source":"index.js","original":{"line":44,"column":43}},{"name":"post","generated":{"line":43,"column":341},"source":"index.js","original":{"line":44,"column":56}},{"name":"selftext","generated":{"line":43,"column":346},"source":"index.js","original":{"line":44,"column":61}},{"generated":{"line":43,"column":354},"source":"index.js","original":{"line":44,"column":43}},{"generated":{"line":43,"column":356},"source":"index.js","original":{"line":44,"column":71}},{"generated":{"line":43,"column":359},"source":"index.js","original":{"line":44,"column":43}},{"generated":{"line":43,"column":360},"source":"index.js","original":{"line":39,"column":16}},{"name":"post","generated":{"line":43,"column":402},"source":"index.js","original":{"line":45,"column":30}},{"name":"url","generated":{"line":43,"column":407},"source":"index.js","original":{"line":45,"column":35}},{"generated":{"line":43,"column":410},"source":"index.js","original":{"line":39,"column":16}},{"name":"post","generated":{"line":43,"column":568},"source":"index.js","original":{"line":47,"column":70}},{"name":"subreddit","generated":{"line":43,"column":573},"source":"index.js","original":{"line":47,"column":75}},{"generated":{"line":43,"column":582},"source":"index.js","original":{"line":39,"column":16}},{"name":"post","generated":{"line":43,"column":659},"source":"index.js","original":{"line":48,"column":61}},{"name":"score","generated":{"line":43,"column":664},"source":"index.js","original":{"line":48,"column":66}},{"generated":{"line":43,"column":669},"source":"index.js","original":{"line":39,"column":16}},{"generated":{"line":44,"column":0},"source":"index.js","original":{"line":52,"column":13}},{"generated":{"line":44,"column":9},"source":"index.js","original":{"line":36,"column":12}},{"name":"output","generated":{"line":45,"column":0},"source":"index.js","original":{"line":53,"column":12}},{"generated":{"line":45,"column":18},"source":"index.js","original":{"line":53,"column":22}},{"generated":{"line":45,"column":26},"source":"index.js","original":{"line":53,"column":12}},{"name":"document","generated":{"line":46,"column":0},"source":"index.js","original":{"line":54,"column":12}},{"name":"getElementById","generated":{"line":46,"column":17},"source":"index.js","original":{"line":54,"column":21}},{"generated":{"line":46,"column":31},"source":"index.js","original":{"line":54,"column":12}},{"generated":{"line":46,"column":32},"source":"index.js","original":{"line":54,"column":36}},{"generated":{"line":46,"column":41},"source":"index.js","original":{"line":54,"column":12}},{"name":"innerHTML","generated":{"line":46,"column":43},"source":"index.js","original":{"line":54,"column":47}},{"generated":{"line":46,"column":52},"source":"index.js","original":{"line":54,"column":12}},{"name":"output","generated":{"line":46,"column":55},"source":"index.js","original":{"line":54,"column":59}},{"generated":{"line":46,"column":61},"source":"index.js","original":{"line":54,"column":12}},{"generated":{"line":47,"column":0},"source":"index.js","original":{"line":55,"column":9}},{"generated":{"line":47,"column":5},"source":"index.js","original":{"line":31,"column":4}},{"generated":{"line":48,"column":0},"source":"index.js","original":{"line":57,"column":1}},{"generated":{"line":48,"column":1},"source":"index.js","original":{"line":8,"column":0}},{"generated":{"line":50,"column":0},"source":"index.js","original":{"line":59,"column":0}},{"generated":{"line":52,"column":0},"source":"index.js","original":{"line":61,"column":0}},{"name":"showMessage","generated":{"line":52,"column":9},"source":"index.js","original":{"line":61,"column":9}},{"generated":{"line":52,"column":20},"source":"index.js","original":{"line":61,"column":0}},{"name":"message","generated":{"line":52,"column":21},"source":"index.js","original":{"line":61,"column":21}},{"generated":{"line":52,"column":28},"source":"index.js","original":{"line":61,"column":0}},{"name":"className","generated":{"line":52,"column":30},"source":"index.js","original":{"line":61,"column":30}},{"generated":{"line":52,"column":39},"source":"index.js","original":{"line":61,"column":0}},{"generated":{"line":52,"column":41},"source":"index.js","original":{"line":61,"column":41}},{"generated":{"line":53,"column":0},"source":"index.js","original":{"line":62,"column":4}},{"generated":{"line":54,"column":0},"source":"index.js","original":{"line":63,"column":4}},{"name":"div","generated":{"line":54,"column":8},"source":"index.js","original":{"line":63,"column":10}},{"name":"document","generated":{"line":54,"column":14},"source":"index.js","original":{"line":63,"column":16}},{"name":"createElement","generated":{"line":54,"column":23},"source":"index.js","original":{"line":63,"column":25}},{"generated":{"line":54,"column":36},"source":"index.js","original":{"line":63,"column":16}},{"generated":{"line":54,"column":37},"source":"index.js","original":{"line":63,"column":39}},{"generated":{"line":54,"column":42},"source":"index.js","original":{"line":63,"column":16}},{"generated":{"line":54,"column":43},"source":"index.js","original":{"line":63,"column":4}},{"generated":{"line":55,"column":0},"source":"index.js","original":{"line":64,"column":4}},{"name":"div","generated":{"line":56,"column":0},"source":"index.js","original":{"line":65,"column":4}},{"name":"className","generated":{"line":56,"column":8},"source":"index.js","original":{"line":65,"column":8}},{"generated":{"line":56,"column":17},"source":"index.js","original":{"line":65,"column":4}},{"name":"className","generated":{"line":56,"column":31},"source":"index.js","original":{"line":65,"column":29}},{"generated":{"line":56,"column":40},"source":"index.js","original":{"line":65,"column":4}},{"generated":{"line":57,"column":0},"source":"index.js","original":{"line":66,"column":4}},{"name":"div","generated":{"line":58,"column":0},"source":"index.js","original":{"line":67,"column":4}},{"name":"appendChild","generated":{"line":58,"column":8},"source":"index.js","original":{"line":67,"column":8}},{"generated":{"line":58,"column":19},"source":"index.js","original":{"line":67,"column":4}},{"name":"document","generated":{"line":58,"column":20},"source":"index.js","original":{"line":67,"column":20}},{"name":"createTextNode","generated":{"line":58,"column":29},"source":"index.js","original":{"line":67,"column":29}},{"generated":{"line":58,"column":43},"source":"index.js","original":{"line":67,"column":20}},{"name":"message","generated":{"line":58,"column":44},"source":"index.js","original":{"line":67,"column":44}},{"generated":{"line":58,"column":51},"source":"index.js","original":{"line":67,"column":20}},{"generated":{"line":58,"column":52},"source":"index.js","original":{"line":67,"column":4}},{"generated":{"line":59,"column":0},"source":"index.js","original":{"line":68,"column":4}},{"generated":{"line":60,"column":0},"source":"index.js","original":{"line":69,"column":4}},{"name":"searchContainer","generated":{"line":60,"column":8},"source":"index.js","original":{"line":69,"column":10}},{"name":"document","generated":{"line":60,"column":26},"source":"index.js","original":{"line":69,"column":28}},{"name":"getElementById","generated":{"line":60,"column":35},"source":"index.js","original":{"line":69,"column":37}},{"generated":{"line":60,"column":49},"source":"index.js","original":{"line":69,"column":28}},{"generated":{"line":60,"column":50},"source":"index.js","original":{"line":69,"column":52}},{"generated":{"line":60,"column":68},"source":"index.js","original":{"line":69,"column":28}},{"generated":{"line":60,"column":69},"source":"index.js","original":{"line":69,"column":4}},{"generated":{"line":61,"column":0},"source":"index.js","original":{"line":70,"column":4}},{"generated":{"line":62,"column":0},"source":"index.js","original":{"line":71,"column":4}},{"name":"search","generated":{"line":62,"column":8},"source":"index.js","original":{"line":71,"column":10}},{"name":"document","generated":{"line":62,"column":17},"source":"index.js","original":{"line":71,"column":19}},{"name":"getElementById","generated":{"line":62,"column":26},"source":"index.js","original":{"line":71,"column":28}},{"generated":{"line":62,"column":40},"source":"index.js","original":{"line":71,"column":19}},{"generated":{"line":62,"column":41},"source":"index.js","original":{"line":71,"column":43}},{"generated":{"line":62,"column":49},"source":"index.js","original":{"line":71,"column":19}},{"generated":{"line":62,"column":50},"source":"index.js","original":{"line":71,"column":4}},{"generated":{"line":64,"column":0},"source":"index.js","original":{"line":73,"column":4}},{"name":"searchContainer","generated":{"line":65,"column":0},"source":"index.js","original":{"line":74,"column":4}},{"name":"insertBefore","generated":{"line":65,"column":20},"source":"index.js","original":{"line":74,"column":20}},{"generated":{"line":65,"column":32},"source":"index.js","original":{"line":74,"column":4}},{"name":"div","generated":{"line":65,"column":33},"source":"index.js","original":{"line":74,"column":33}},{"generated":{"line":65,"column":36},"source":"index.js","original":{"line":74,"column":4}},{"name":"search","generated":{"line":65,"column":38},"source":"index.js","original":{"line":74,"column":38}},{"generated":{"line":65,"column":44},"source":"index.js","original":{"line":74,"column":4}},{"generated":{"line":67,"column":0},"source":"index.js","original":{"line":76,"column":4}},{"name":"setTimeout","generated":{"line":68,"column":0},"source":"index.js","original":{"line":77,"column":4}},{"generated":{"line":68,"column":15},"source":"index.js","original":{"line":77,"column":15}},{"generated":{"line":69,"column":0},"source":"index.js","original":{"line":77,"column":15}},{"name":"document","generated":{"line":69,"column":15},"source":"index.js","original":{"line":77,"column":21}},{"name":"querySelector","generated":{"line":69,"column":24},"source":"index.js","original":{"line":77,"column":30}},{"generated":{"line":69,"column":37},"source":"index.js","original":{"line":77,"column":21}},{"generated":{"line":69,"column":38},"source":"index.js","original":{"line":77,"column":44}},{"generated":{"line":69,"column":46},"source":"index.js","original":{"line":77,"column":21}},{"name":"remove","generated":{"line":69,"column":48},"source":"index.js","original":{"line":77,"column":54}},{"generated":{"line":69,"column":54},"source":"index.js","original":{"line":77,"column":21}},{"generated":{"line":69,"column":56},"source":"index.js","original":{"line":77,"column":15}},{"generated":{"line":70,"column":0},"source":"index.js","original":{"line":77,"column":15}},{"generated":{"line":70,"column":5},"source":"index.js","original":{"line":77,"column":4}},{"generated":{"line":70,"column":7},"source":"index.js","original":{"line":77,"column":64}},{"generated":{"line":70,"column":11},"source":"index.js","original":{"line":77,"column":4}},{"generated":{"line":71,"column":0},"source":"index.js","original":{"line":78,"column":1}},{"generated":{"line":72,"column":0},"source":"index.js","original":{"line":79,"column":0}},{"generated":{"line":74,"column":0},"source":"index.js","original":{"line":81,"column":0}},{"name":"truncateText","generated":{"line":74,"column":9},"source":"index.js","original":{"line":81,"column":9}},{"generated":{"line":74,"column":21},"source":"index.js","original":{"line":81,"column":0}},{"name":"text","generated":{"line":74,"column":22},"source":"index.js","original":{"line":81,"column":22}},{"generated":{"line":74,"column":26},"source":"index.js","original":{"line":81,"column":0}},{"name":"limit","generated":{"line":74,"column":28},"source":"index.js","original":{"line":81,"column":28}},{"generated":{"line":74,"column":33},"source":"index.js","original":{"line":81,"column":0}},{"generated":{"line":74,"column":35},"source":"index.js","original":{"line":81,"column":35}},{"generated":{"line":75,"column":0},"source":"index.js","original":{"line":82,"column":4}},{"name":"shortend","generated":{"line":75,"column":8},"source":"index.js","original":{"line":82,"column":10}},{"name":"text","generated":{"line":75,"column":19},"source":"index.js","original":{"line":82,"column":21}},{"name":"indexOf","generated":{"line":75,"column":24},"source":"index.js","original":{"line":82,"column":26}},{"generated":{"line":75,"column":31},"source":"index.js","original":{"line":82,"column":21}},{"generated":{"line":75,"column":32},"source":"index.js","original":{"line":82,"column":34}},{"generated":{"line":75,"column":35},"source":"index.js","original":{"line":82,"column":21}},{"name":"limit","generated":{"line":75,"column":37},"source":"index.js","original":{"line":82,"column":39}},{"generated":{"line":75,"column":42},"source":"index.js","original":{"line":82,"column":21}},{"generated":{"line":75,"column":43},"source":"index.js","original":{"line":82,"column":4}},{"generated":{"line":77,"column":0},"source":"index.js","original":{"line":84,"column":4}},{"name":"shortend","generated":{"line":77,"column":8},"source":"index.js","original":{"line":84,"column":7}},{"generated":{"line":77,"column":20},"source":"index.js","original":{"line":84,"column":19}},{"generated":{"line":77,"column":21},"source":"index.js","original":{"line":84,"column":20}},{"generated":{"line":77,"column":22},"source":"index.js","original":{"line":84,"column":4}},{"generated":{"line":77,"column":24},"source":"index.js","original":{"line":84,"column":23}},{"name":"text","generated":{"line":77,"column":31},"source":"index.js","original":{"line":84,"column":30}},{"generated":{"line":77,"column":35},"source":"index.js","original":{"line":84,"column":23}},{"generated":{"line":78,"column":0},"source":"index.js","original":{"line":85,"column":4}},{"name":"text","generated":{"line":78,"column":11},"source":"index.js","original":{"line":85,"column":11}},{"name":"substring","generated":{"line":78,"column":16},"source":"index.js","original":{"line":85,"column":16}},{"generated":{"line":78,"column":25},"source":"index.js","original":{"line":85,"column":11}},{"generated":{"line":78,"column":26},"source":"index.js","original":{"line":85,"column":26}},{"generated":{"line":78,"column":27},"source":"index.js","original":{"line":85,"column":11}},{"name":"shortend","generated":{"line":78,"column":29},"source":"index.js","original":{"line":85,"column":29}},{"generated":{"line":78,"column":37},"source":"index.js","original":{"line":85,"column":11}},{"generated":{"line":78,"column":38},"source":"index.js","original":{"line":85,"column":4}},{"generated":{"line":79,"column":0},"source":"index.js","original":{"line":86,"column":1}}],"sources":{"index.js":"import reddit from './redditAPI';\n\nconst searchForm = document.getElementById('search-form');\nconst searchInput = document.getElementById('search-input');\n\n\n//Form Event Listener\nsearchForm.addEventListener('submit', e => {\n    e.preventDefault();\n   \n    //Get search term\n    const searchTerm = searchInput.value;\n\n    //Get sort\n    const sortBy = document.querySelector('input[name=\"sortby\"]:checked').value;\n\n    // Get Limit\n    const searchLimit = document.getElementById('limit').value;\n  \n    //Check Input\n\n    if(searchTerm === '') {\n        //Show message\n        showMessage('Please add a search term!', 'alert-danger')\n    }\n\n    //Clear input\n    searchInput.value = '';\n\n    //Search Reddit\n    reddit.search(searchTerm, searchLimit, sortBy)\n        .then(results => {\n            let output = '<div class=\"card-columns\">';\n            //Loop through posts\n\n            results.forEach(post => {\n                //Check for image;\n                const image = post.preview ? post.preview.images[0].source.url : 'https://marketingland.com/wp-content/ml-loads/2014/07/reddit-combo-1920-800x450.png';\n                output += `\n                <div class=\"card\" >\n                    <img class=\"card-img-top\" src=${image} alt=\"Card image cap\">\n                    <div class=\"card-body\">\n                    <h5 class=\"card-title\">${truncateText(post.title, 50)}...</h5>\n                    <p class=\"card-text\">${truncateText(post.selftext, 100)}</p>\n                    <a href=${post.url} target=\"_blank\" class=\"btn btn-primary\">Read More</a>\n                    <hr>\n                    <span class=\"badge badge-secondary\"> Subreddit: ${post.subreddit} </span>\n                    <span class=\"badge badge-dark\"> Score: ${post.score} </span>\n                    </div>\n                </div>\n                `\n            })\n            output += '</div>';\n            document.getElementById('results').innerHTML = output;\n        })\n\n});\n\n//Show Message\n\nfunction showMessage(message, className) {\n    //create div\n    const div = document.createElement('div');\n    //Add classes\n    div.className = `alert ${className}`;\n    //Add text\n    div.appendChild(document.createTextNode(message));\n    //Get Parent \n    const searchContainer = document.getElementById('search-container');\n    //Get Search\n    const search = document.getElementById('search');\n\n    //Insert Message\n    searchContainer.insertBefore(div, search);\n    \n    //Timeout alert\n    setTimeout(() => document.querySelector('.alert').remove(), 3000);\n}\n//Truncate Text\n\nfunction truncateText(text, limit) {\n    const shortend = text.indexOf(' ', limit);\n\n    if(shortend == -1) return text;\n    return text.substring(0, shortend);\n}"},"lineCount":null}},"hash":"5160b099b92c4a9ada55ccb5b11bf2da","cacheData":{"env":{}}}